mybot/__init__.py
mybot/bots/__init__.py
mybot/plugins/__init__.py
mybot-0.0.1.dist-info/LICENSE
mybot-0.0.1.dist-info/METADATA
mybot-0.0.1.dist-info/WHEEL
mybot-0.0.1.dist-info/top_level.txt
mybot-0.0.1.dist-info/RECORD
