Metadata-Version: 2.1
Name: mybot
Version: 0.0.1
Summary: MyBot package for creating custom bots
Home-page: https://github.com/YaserJaradeh/mybot
Author: Yaser Jaradeh
Author-email: yaser.jaradeh@gmail.com
License: UNKNOWN
Project-URL: Bug Tracker, https://github.com/YaserJaradeh/mybot/issues
Platform: UNKNOWN
Classifier: Programming Language :: Python :: 3
Classifier: License :: OSI Approved :: Apache Software License
Classifier: Operating System :: OS Independent
Requires-Python: >=3.6
